{
"station": "Grove (Cygnet Area)",
"coordinates": "-43.1647,147.0584",
"temperature": "5.8",
"apparent_temperature": "2.6",
"humidity": "82",
"wind_direction": "W",
"wind_speed_kmh": "9",
"wind_gust_kmh": "19",
"pressure_hpa": "N/A",
"rainfall_mm": "0.8",
"conditions": "-",
"weather_emoji": "☀️",
"comfort_level": "Cold ❄️",
"observation_time": "20250917123000",
"updated_at": "2025-09-17T12:42:06Z",
"visualizations": {
  "temperature_bar": "█░░░░░░░░░",
  "humidity_bar": "████████░░",
  "wind_bar": "█░░░░░░░░░"
}
}
